galbi/__init__.py
galbi/cli.py
galbi-1.0.0.dist-info/METADATA
galbi-1.0.0.dist-info/WHEEL
galbi-1.0.0.dist-info/entry_points.txt
galbi-1.0.0.dist-info/top_level.txt
galbi-1.0.0.dist-info/RECORD
