Metadata-Version: 2.1
Name: galbi
Version: 1.0.0
Summary: Galbi CLI
Home-page: UNKNOWN
License: UNKNOWN
Platform: UNKNOWN
Requires-Dist: click (>=7.1.2)
Requires-Dist: requests (>=2.25.0)
